fluentui/__init__.py
fluentui/assets/__init__.py
fluentui/assets/res.py
fluentui/assets/res.qrc
fluentui/assets/icons/chevron-down-14.svg
fluentui/assets/icons/chevron-down-20.svg
fluentui/assets/icons/chevron-up-14.svg
fluentui/assets/icons/image-256.svg
fluentui/assets/icons/radio-checked-16.svg
fluentui/assets/icons/radio-checked-hover-16.svg
fluentui/assets/icons/radio-checked-pressed-16.svg
fluentui/assets/icons/radio-uncheck-16.svg
fluentui/assets/icons/radio-uncheck-hover-16.svg
fluentui/assets/icons/radio-uncheck-pressed-16.svg
fluentui/assets/icons/slider-20.svg
fluentui/assets/icons/slider-hover-20.svg
fluentui/assets/theme/color.py
fluentui/assets/theme/qss.py
fluentui/core/__init__.py
fluentui/core/file.py
fluentui/core/itemmodels.py
fluentui/core/margin.py
fluentui/core/namespace.py
fluentui/core/object.py
fluentui/core/size.py
fluentui/core/url.py
fluentui/gui/__init__.py
fluentui/gui/action.py
fluentui/gui/color.py
fluentui/gui/desktop_services.py
fluentui/gui/font.py
fluentui/gui/icon.py
fluentui/gui/item.py
fluentui/gui/itemmodels.py
fluentui/gui/pixmap.py
fluentui/network/__init__.py
fluentui/network/request.py
fluentui/network/socket.py
fluentui/widgets/ImageLabel.py
fluentui/widgets/ImageViewer.py
fluentui/widgets/__init__.py
fluentui/widgets/app.py
fluentui/widgets/button.py
fluentui/widgets/combo_box.py
fluentui/widgets/container.py
fluentui/widgets/frame.py
fluentui/widgets/input.py
fluentui/widgets/item_delete.py
fluentui/widgets/item_view.py
fluentui/widgets/layout.py
fluentui/widgets/message_bar.py
fluentui/widgets/object.py
fluentui/widgets/widget.py
fluentui-0.0.45.dist-info/METADATA
fluentui-0.0.45.dist-info/WHEEL
fluentui-0.0.45.dist-info/RECORD
