Metadata-Version: 2.3
Name: fluentui
Version: 0.0.45
Requires-Python: <3.13,>=3.9
Requires-Dist: beautifulsoup4>=4.12.3
Requires-Dist: polars-lts-cpu>=1.14.0
Requires-Dist: pydantic>=2.9.2
Requires-Dist: pyside6>=6.8.0.2
Requires-Dist: selectolax>=0.3.26
